grib_check/Assert.py
grib_check/CheckEngine.py
grib_check/FileScanner.py
grib_check/Grib.py
grib_check/GribCheck.py
grib_check/KeyValue.py
grib_check/LookupTable.py
grib_check/Message.py
grib_check/Report.py
grib_check/TermColor.py
grib_check/Test.py
grib_check/TiggeName.py
grib_check/ValueFormat.py
grib_check/__init__.py
grib_check/checker/Crra.py
grib_check/checker/CrraParameters.jsonnet
grib_check/checker/GeneralChecks.py
grib_check/checker/Lam.py
grib_check/checker/Parameter.libsonnet
grib_check/checker/S2S.py
grib_check/checker/S2SRefcst.py
grib_check/checker/Tigge.py
grib_check/checker/TiggeParameters.jsonnet
grib_check/checker/Uerra.py
grib_check/checker/WmoParameters.jsonnet
grib_check/checker/Wpmip.py
grib_check/checker/WpmipParameters.jsonnet
grib_check-0.0.6.dist-info/licenses/AUTHORS
grib_check-0.0.6.dist-info/licenses/LICENCE
grib_check-0.0.6.dist-info/licenses/NOTICE
grib_check-0.0.6.dist-info/METADATA
grib_check-0.0.6.dist-info/WHEEL
grib_check-0.0.6.dist-info/entry_points.txt
grib_check-0.0.6.dist-info/top_level.txt
grib_check-0.0.6.dist-info/RECORD
