Metadata-Version: 2.4
Name: grib-check
Version: 0.0.6
Summary: Tools for checking GRIB files
Author-email: "European Centre for Medium-Range Weather Forecasts (ECMWF)" <software.support@ecmwf.int>
License: Apache License Version 2.0
Project-URL: Documentation, https://github.com/ecmwf/grib-check
Project-URL: Homepage, https://github.com/ecmwf/grib-check
Project-URL: Issues, https://github.com/ecmwf/grib-check/issues
Project-URL: Repository, https://github.com/ecmwf/grib-check
Classifier: Development Status :: 3 - Alpha
Classifier: Intended Audience :: End Users/Desktop
Classifier: License :: OSI Approved :: Apache Software License
Classifier: Operating System :: OS Independent
Classifier: Programming Language :: Python :: 3 :: Only
Classifier: Programming Language :: Python :: 3.9
Classifier: Programming Language :: Python :: 3.10
Classifier: Programming Language :: Python :: 3.11
Classifier: Programming Language :: Python :: 3.12
Classifier: Programming Language :: Python :: 3.13
Classifier: Programming Language :: Python :: Implementation :: PyPy
Requires-Python: >=3.8
License-File: LICENCE
License-File: NOTICE
License-File: AUTHORS
Requires-Dist: eccodes>=2.27.0
Requires-Dist: jsonnet
Provides-Extra: test
Requires-Dist: pytest; extra == "test"
Dynamic: license-file
